setup.cfg
setup.py
janis/__init__.py
janis/janis.py
janis.egg-info/PKG-INFO
janis.egg-info/SOURCES.txt
janis.egg-info/dependency_links.txt
janis.egg-info/requires.txt
janis.egg-info/top_level.txt