Metadata-Version: 1.1
Name: janis
Version: 0.0.3
Summary: A toolkit for creating a hybrid Chatbot + Human UX
Home-page: https://github.com/janis-ai/janis-python
Author: Michael Nathanson
Author-email: mike@janis.ai
License: UNKNOWN
Download-URL: https://github.com/janis-ai/janis-python/tarball/0.0.3
Keywords: chatbot,bot,opitmization,bot,analytics
Platform: UNKNOWN
